{
  "bpm": 230,
  "offset": 1.3,
  "notes": [
    {"time":0,"key":"j","type":"tap"},
    {"time":0,"key":"k","type":"tap"},
    {"time":2,"key":"d","type":"tap"},
    {"time":2,"key":"f","type":"tap"},
    {"time":3.5,"key":"j","type":"tap"},
    {"time":3.5,"key":"k","type":"tap"},
    {"time":6,"key":"f","type":"tap"},
    {"time":6,"key":"d","type":"tap"},
    {"time":8,"key":"d","type":"tap"},
    {"time":9.5,"key":"f","type":"tap"},
    {"time":11.5,"key":"j","type":"tap"},
    {"time":14,"key":"k","type":"flick"},
    {"time":16,"key":"k","type":"hold","end":22},
    {"time":17.5,"key":"j","type":"hold","end":22},
    {"time":19.5,"key":"f","type":"hold","end":22},
    {"time":22,"key":"d","type":"flick"},
    {"time":24,"key":"j","type":"tap"},
    {"time":24,"key":"d","type":"tap"},
    {"time":24,"key":"f","type":"tap"},
    {"time":25.5,"key":"f","type":"tap"},
    {"time":25.5,"key":"k","type":"tap"},
    {"time":25.5,"key":"j","type":"tap"},
    {"time":27.5,"key":"j","type":"tap"},
    {"time":27.5,"key":"f","type":"tap"},
    {"time":27.5,"key":"d","type":"tap"},
    {"time":30,"key":"d","type":"flick"},
    {"time":30,"key":"f","type":"flick"},
    {"time":30,"key":"j","type":"flick"},
    {"time":30,"key":"k","type":"flick"},
    {"time":32,"key":"k","type":"tap"},
    {"time":32,"key":"d","type":"hold","end":38},
    {"time":32,"key":"f","type":"hold","end":38},
    {"time":33.5,"key":"j","type":"tap"},
    {"time":36,"key":"k","type":"tap"},
    {"time":38,"key":"j","type":"tap"},
    {"time":40,"key":"d","type":"tap"},
    {"time":40,"key":"j","type":"hold","end":46},
    {"time":40,"key":"k","type":"hold","end":46},
    {"time":41.5,"key":"f","type":"tap"},
    {"time":43.5,"key":"d","type":"tap"},
    {"time":46,"key":"f","type":"tap"},
    {"time":48,"key":"j","type":"tap"},
    {"time":48,"key":"k","type":"hold","end":57.5},
    {"time":48,"key":"d","type":"hold","end":57.5},
    {"time":49.5,"key":"f","type":"tap"},
    {"time":51.5,"key":"j","type":"tap"},
    {"time":54,"key":"f","type":"tap"},
    {"time":56,"key":"j","type":"tap"},
    {"time":57.5,"key":"f","type":"tap"},
    {"time":60,"key":"d","type":"tap"},
    {"time":60,"key":"f","type":"tap"},
    {"time":61,"key":"j","type":"tap"},
    {"time":61,"key":"k","type":"tap"},
    {"time":62,"key":"f","type":"tap"},
    {"time":62,"key":"d","type":"tap"},
    {"time":63,"key":"j","type":"tap"},
    {"time":63,"key":"k","type":"tap"},
    {"time":64,"key":"d","type":"tap"},
    {"time":64,"key":"f","type":"tap"},
    {"time":65,"key":"j","type":"tap"},
    {"time":65,"key":"k","type":"tap"},
    {"time":66,"key":"d","type":"tap"},
    {"time":66,"key":"f","type":"tap"},
    {"time":67,"key":"j","type":"tap"},
    {"time":67,"key":"k","type":"tap"},
    {"time":68,"key":"d","type":"hold","end":70},
    {"time":68,"key":"f","type":"hold","end":70},
    {"time":70,"key":"j","type":"hold","end":72},
    {"time":70,"key":"k","type":"hold","end":72},
    {"time":72,"key":"d","type":"hold","end":74},
    {"time":72,"key":"f","type":"hold","end":74},
    {"time":74,"key":"j","type":"hold","end":76},
    {"time":74,"key":"k","type":"hold","end":76},
    {"time":76,"key":"d","type":"hold","end":77},
    {"time":76,"key":"f","type":"hold","end":77},
    {"time":77,"key":"j","type":"hold","end":78},
    {"time":77,"key":"k","type":"hold","end":78},
    {"time":78,"key":"d","type":"hold","end":79},
    {"time":78,"key":"f","type":"hold","end":79},
    {"time":79,"key":"j","type":"hold","end":80},
    {"time":79,"key":"k","type":"hold","end":80},
    {"time":80,"key":"d","type":"hold","end":81},
    {"time":80,"key":"f","type":"hold","end":81},
    {"time":81,"key":"j","type":"hold","end":82},
    {"time":81,"key":"k","type":"hold","end":82},
    {"time":82,"key":"f","type":"hold","end":83},
    {"time":82,"key":"d","type":"hold","end":83},
    {"time":83,"key":"j","type":"hold","end":84},
    {"time":83,"key":"k","type":"hold","end":84},
    {"time":84,"key":"d","type":"flick"},
    {"time":84,"key":"f","type":"flick"},
    {"time":85,"key":"j","type":"flick"},
    {"time":85,"key":"k","type":"flick"},
    {"time":86,"key":"d","type":"flick"},
    {"time":86,"key":"f","type":"flick"},
    {"time":87,"key":"j","type":"flick"},
    {"time":87,"key":"k","type":"flick"},
    {"time":88,"key":"d","type":"flick"},
    {"time":88,"key":"f","type":"flick"},
    {"time":88,"key":"j","type":"flick"},
    {"time":88,"key":"k","type":"flick"},
    {"time":89.5,"key":"d","type":"flick"},
    {"time":89.5,"key":"f","type":"flick"},
    {"time":89.5,"key":"j","type":"flick"},
    {"time":89.5,"key":"k","type":"flick"},
    {"time":91,"key":"k","type":"hold","end":92},
    {"time":91,"key":"j","type":"hold","end":92},
    {"time":91,"key":"f","type":"hold","end":92},
    {"time":91,"key":"d","type":"hold","end":92},
    {"time":93,"key":"j","type":"tap"},
    {"time":93,"key":"k","type":"tap"},
    {"time":94,"key":"d","type":"tap"},
    {"time":94,"key":"f","type":"tap"},
    {"time":95,"key":"j","type":"tap"},
    {"time":95,"key":"k","type":"tap"},
    {"time":96,"key":"d","type":"tap"},
    {"time":96,"key":"f","type":"tap"},
    {"time":97,"key":"j","type":"tap"},
    {"time":97,"key":"k","type":"tap"},
    {"time":98,"key":"d","type":"tap"},
    {"time":98,"key":"f","type":"tap"},
    {"time":99,"key":"j","type":"tap"},
    {"time":99,"key":"k","type":"tap"},
    {"time":100,"key":"d","type":"tap"},
    {"time":100,"key":"f","type":"tap"},
    {"time":101,"key":"j","type":"tap"},
    {"time":101,"key":"k","type":"tap"},
    {"time":102,"key":"d","type":"tap"},
    {"time":102,"key":"f","type":"tap"},
    {"time":103,"key":"j","type":"hold","end":105},
    {"time":103,"key":"k","type":"hold","end":105},
    {"time":105,"key":"d","type":"hold","end":106},
    {"time":105,"key":"f","type":"hold","end":106},
    {"time":107,"key":"k","type":"tap"},
    {"time":108,"key":"j","type":"tap"},
    {"time":108.5,"key":"k","type":"flick"},
    {"time":110,"key":"d","type":"tap"},
    {"time":110,"key":"f","type":"tap"},
    {"time":111,"key":"j","type":"tap"},
    {"time":111,"key":"k","type":"tap"},
    {"time":112,"key":"d","type":"tap"},
    {"time":112,"key":"f","type":"tap"},
    {"time":113,"key":"j","type":"tap"},
    {"time":113,"key":"k","type":"tap"},
    {"time":114,"key":"d","type":"tap"},
    {"time":115,"key":"f","type":"tap"},
    {"time":116,"key":"d","type":"flick"},
    {"time":117,"key":"d","type":"hold","end":118},
    {"time":117,"key":"f","type":"hold","end":118},
    {"time":119,"key":"j","type":"hold","end":120},
    {"time":119,"key":"k","type":"hold","end":120},
    {"time":121,"key":"d","type":"tap"},
    {"time":122,"key":"f","type":"tap"},
    {"time":123,"key":"d","type":"flick"},
    {"time":124,"key":"j","type":"hold","end":125},
    {"time":124,"key":"k","type":"hold","end":125},
    {"time":126,"key":"d","type":"tap"},
    {"time":126,"key":"f","type":"tap"},
    {"time":127,"key":"j","type":"tap"},
    {"time":127,"key":"k","type":"tap"},
    {"time":128,"key":"d","type":"tap"},
    {"time":128,"key":"f","type":"tap"},
    {"time":129,"key":"j","type":"tap"},
    {"time":129,"key":"k","type":"tap"},
    {"time":130,"key":"d","type":"tap"},
    {"time":130,"key":"f","type":"tap"},
    {"time":131,"key":"k","type":"flick"},
    {"time":131,"key":"j","type":"flick"},
    {"time":132.5,"key":"d","type":"hold","end":133.5},
    {"time":132.5,"key":"f","type":"hold","end":133.5},
    {"time":132.5,"key":"j","type":"hold","end":133.5},
    {"time":132.5,"key":"k","type":"hold","end":133.5},
    {"time":134.5,"key":"j","type":"flick"},
    {"time":134.5,"key":"k","type":"flick"},
    {"time":134.5,"key":"f","type":"flick"},
    {"time":134.5,"key":"d","type":"flick"},
    {"time":135.5,"key":"d","type":"flick"},
    {"time":135.5,"key":"f","type":"flick"},
    {"time":135.5,"key":"j","type":"flick"},
    {"time":135.5,"key":"k","type":"flick"},
    {"time":136.5,"key":"k","type":"hold","end":137.5},
    {"time":137.5,"key":"j","type":"hold","end":138.5},
    {"time":138.5,"key":"f","type":"hold","end":139.5},
    {"time":139.5,"key":"d","type":"hold","end":140.5},
    {"time":140.5,"key":"k","type":"flick"},
    {"time":140.5,"key":"j","type":"flick"},
    {"time":140.5,"key":"f","type":"flick"},
    {"time":141.5,"key":"d","type":"hold","end":142.5},
    {"time":141.5,"key":"f","type":"hold","end":142.5},
    {"time":143.5,"key":"k","type":"tap"},
    {"time":144.5,"key":"d","type":"tap"},
    {"time":145.5,"key":"k","type":"tap"},
    {"time":146.5,"key":"d","type":"tap"},
    {"time":147.5,"key":"f","type":"tap"},
    {"time":148.5,"key":"j","type":"tap"},
    {"time":149.5,"key":"k","type":"hold","end":150.5},
    {"time":149.5,"key":"d","type":"flick"},
    {"time":150.5,"key":"j","type":"hold","end":151.5},
    {"time":151.5,"key":"f","type":"hold","end":152.5},
    {"time":152.5,"key":"j","type":"hold","end":153.5},
    {"time":153.5,"key":"k","type":"hold","end":154.5},
    {"time":154.5,"key":"d","type":"flick"},
    {"time":155.5,"key":"d","type":"flick"},
    {"time":155.5,"key":"f","type":"flick"},
    {"time":155.5,"key":"k","type":"flick"},
    {"time":155.5,"key":"j","type":"flick"},
    {"time":157,"key":"k","type":"hold","end":158.5},
    {"time":157,"key":"j","type":"hold","end":158.5},
    {"time":158.5,"key":"f","type":"hold","end":159.5},
    {"time":160,"key":"d","type":"tap"},
    {"time":161,"key":"j","type":"tap"},
    {"time":161,"key":"k","type":"tap"},
    {"time":162,"key":"j","type":"tap"},
    {"time":162,"key":"k","type":"tap"},
    {"time":162.5,"key":"d","type":"hold","end":163.5},
    {"time":163.5,"key":"f","type":"tap"},
    {"time":164.5,"key":"j","type":"flick"},
    {"time":164.5,"key":"k","type":"flick"},
    {"time":166,"key":"d","type":"hold","end":167},
    {"time":166,"key":"f","type":"hold","end":167},
    {"time":167,"key":"k","type":"tap"},
    {"time":168,"key":"j","type":"tap"},
    {"time":169,"key":"k","type":"tap"},
    {"time":170,"key":"d","type":"tap"},
    {"time":171,"key":"f","type":"tap"},
    {"time":172,"key":"k","type":"flick"},
    {"time":172,"key":"j","type":"flick"},
    {"time":173,"key":"d","type":"hold","end":174},
    {"time":173,"key":"f","type":"hold","end":174},
    {"time":175,"key":"k","type":"tap"},
    {"time":176,"key":"j","type":"tap"},
    {"time":177,"key":"f","type":"tap"},
    {"time":178,"key":"d","type":"tap"},
    {"time":179,"key":"f","type":"tap"},
    {"time":180,"key":"d","type":"tap"},
    {"time":180.5,"key":"k","type":"hold","end":182},
    {"time":180.5,"key":"j","type":"hold","end":182},
    {"time":183,"key":"d","type":"flick"},
    {"time":183,"key":"f","type":"flick"},
    {"time":184,"key":"k","type":"hold","end":186},
    {"time":184,"key":"j","type":"hold","end":186},
    {"time":186,"key":"d","type":"hold","end":187},
    {"time":186,"key":"f","type":"hold","end":187},
    {"time":188.5,"key":"d","type":"flick"},
    {"time":188.5,"key":"f","type":"flick"},
    {"time":188.5,"key":"j","type":"flick"},
    {"time":188.5,"key":"k","type":"flick"},
    {"time":189.5,"key":"k","type":"hold","end":192.5},
    {"time":189.5,"key":"j","type":"hold","end":192.5},
    {"time":189.5,"key":"f","type":"tap"},
    {"time":190.5,"key":"d","type":"tap"},
    {"time":191.5,"key":"f","type":"tap"},
    {"time":192.5,"key":"d","type":"tap"},
    {"time":193.5,"key":"f","type":"tap"},
    {"time":194.5,"key":"j","type":"tap"},
    {"time":195.5,"key":"k","type":"tap"},
    {"time":195.5,"key":"d","type":"hold","end":198.5},
    {"time":195.5,"key":"f","type":"hold","end":198.5},
    {"time":196.5,"key":"j","type":"tap"},
    {"time":197.5,"key":"k","type":"tap"},
    {"time":198.5,"key":"j","type":"tap"},
    {"time":199.5,"key":"d","type":"tap"},
    {"time":200.5,"key":"f","type":"tap"},
    {"time":201.5,"key":"j","type":"tap"},
    {"time":202.5,"key":"k","type":"tap"},
    {"time":203.5,"key":"j","type":"tap"},
    {"time":204.5,"key":"k","type":"tap"},
    {"time":205.5,"key":"j","type":"tap"},
    {"time":206.5,"key":"f","type":"tap"},
    {"time":207.5,"key":"d","type":"hold","end":211},
    {"time":208.5,"key":"f","type":"hold","end":211.5},
    {"time":209.5,"key":"j","type":"hold","end":212},
    {"time":210.5,"key":"k","type":"hold","end":212.5},
    {"time":213.5,"key":"d","type":"tap"},
    {"time":214.5,"key":"f","type":"tap"},
    {"time":215.5,"key":"j","type":"tap"},
    {"time":216.5,"key":"k","type":"tap"},
    {"time":218,"key":"d","type":"flick"},
    {"time":218,"key":"f","type":"flick"},
    {"time":218,"key":"j","type":"flick"},
    {"time":218,"key":"k","type":"flick"},
    {"time":218.5,"key":"d","type":"flick"},
    {"time":218.5,"key":"f","type":"flick"},
    {"time":218.5,"key":"k","type":"flick"},
    {"time":218.5,"key":"j","type":"flick"},
    {"time":220,"key":"j","type":"tap"},
    {"time":220,"key":"k","type":"tap"},
    {"time":221,"key":"d","type":"tap"},
    {"time":221,"key":"f","type":"tap"},
    {"time":222,"key":"j","type":"tap"},
    {"time":222,"key":"k","type":"tap"},
    {"time":223,"key":"d","type":"tap"},
    {"time":223,"key":"f","type":"tap"},
    {"time":224,"key":"j","type":"tap"},
    {"time":224,"key":"k","type":"tap"},
    {"time":225,"key":"d","type":"tap"},
    {"time":225,"key":"f","type":"tap"},
    {"time":226,"key":"j","type":"hold","end":228},
    {"time":226,"key":"k","type":"hold","end":228},
    {"time":228,"key":"d","type":"hold","end":230},
    {"time":228,"key":"f","type":"hold","end":230},
    {"time":231,"key":"k","type":"tap"},
    {"time":232,"key":"j","type":"tap"},
    {"time":233,"key":"f","type":"tap"},
    {"time":234,"key":"d","type":"hold","end":236},
    {"time":234,"key":"k","type":"hold","end":236},
    {"time":236,"key":"f","type":"flick"},
    {"time":236,"key":"j","type":"flick"},
    {"time":237,"key":"k","type":"tap"},
    {"time":237,"key":"j","type":"tap"},
    {"time":238,"key":"f","type":"tap"},
    {"time":238,"key":"d","type":"tap"},
    {"time":239,"key":"j","type":"tap"},
    {"time":239,"key":"k","type":"tap"},
    {"time":240,"key":"d","type":"tap"},
    {"time":240,"key":"f","type":"tap"},
    {"time":241,"key":"k","type":"tap"},
    {"time":242,"key":"j","type":"tap"},
    {"time":243,"key":"f","type":"tap"},
    {"time":244,"key":"j","type":"hold","end":246},
    {"time":244,"key":"k","type":"hold","end":246},
    {"time":244,"key":"d","type":"tap"},
    {"time":246,"key":"f","type":"hold","end":247},
    {"time":246,"key":"d","type":"hold","end":247},
    {"time":248,"key":"j","type":"hold","end":249},
    {"time":248,"key":"k","type":"hold","end":249},
    {"time":250,"key":"d","type":"hold","end":252},
    {"time":250,"key":"f","type":"hold","end":252},
    {"time":252,"key":"j","type":"flick"},
    {"time":252,"key":"k","type":"flick"},
    {"time":253,"key":"d","type":"tap"},
    {"time":254,"key":"f","type":"tap"},
    {"time":255,"key":"j","type":"tap"},
    {"time":256,"key":"d","type":"hold","end":257},
    {"time":256,"key":"f","type":"hold","end":257},
    {"time":256,"key":"k","type":"tap"},
    {"time":257,"key":"k","type":"flick"},
    {"time":257,"key":"j","type":"flick"},
    {"time":258,"key":"d","type":"tap"},
    {"time":259,"key":"f","type":"tap"},
    {"time":260,"key":"j","type":"tap"},
    {"time":261,"key":"k","type":"tap"},
    {"time":262,"key":"j","type":"tap"},
    {"time":263,"key":"f","type":"tap"},
    {"time":264,"key":"k","type":"hold","end":265},
    {"time":264,"key":"j","type":"hold","end":265},
    {"time":264,"key":"d","type":"tap"},
    {"time":265,"key":"d","type":"flick"},
    {"time":265,"key":"f","type":"flick"},
    {"time":266,"key":"d","type":"hold","end":267},
    {"time":266,"key":"f","type":"hold","end":267},
    {"time":266,"key":"j","type":"hold","end":267},
    {"time":266,"key":"k","type":"hold","end":267},
    {"time":268,"key":"k","type":"hold","end":269},
    {"time":269,"key":"j","type":"hold","end":270},
    {"time":270,"key":"f","type":"hold","end":271},
    {"time":271,"key":"d","type":"hold","end":272},
    {"time":272,"key":"f","type":"hold","end":273},
    {"time":273,"key":"j","type":"hold","end":274},
    {"time":274,"key":"k","type":"hold","end":275},
    {"time":277,"key":"d","type":"flick"},
    {"time":277,"key":"f","type":"flick"},
    {"time":277,"key":"j","type":"flick"},
    {"time":277,"key":"k","type":"flick"},
    {"time":278,"key":"d","type":"hold","end":280},
    {"time":278,"key":"j","type":"hold","end":280},
    {"time":278,"key":"f","type":"hold","end":280},
    {"time":278,"key":"k","type":"hold","end":280},
    {"time":281,"key":"d","type":"flick"},
    {"time":281,"key":"f","type":"flick"},
    {"time":281,"key":"j","type":"flick"},
    {"time":281,"key":"k","type":"flick"},
    {"time":282,"key":"k","type":"tap"},
    {"time":283,"key":"j","type":"tap"},
    {"time":284,"key":"f","type":"tap"},
    {"time":285,"key":"d","type":"tap"},
    {"time":286,"key":"j","type":"tap"},
    {"time":286,"key":"k","type":"tap"},
    {"time":287,"key":"d","type":"tap"},
    {"time":287,"key":"f","type":"tap"},
    {"time":288,"key":"j","type":"tap"},
    {"time":288,"key":"k","type":"tap"},
    {"time":289,"key":"d","type":"tap"},
    {"time":289,"key":"f","type":"tap"},
    {"time":290,"key":"j","type":"tap"},
    {"time":290,"key":"k","type":"tap"},
    {"time":291,"key":"f","type":"tap"},
    {"time":291,"key":"d","type":"tap"},
    {"time":292,"key":"j","type":"tap"},
    {"time":292,"key":"k","type":"tap"},
    {"time":293,"key":"f","type":"tap"},
    {"time":293,"key":"d","type":"tap"},
    {"time":294,"key":"j","type":"hold","end":296},
    {"time":294,"key":"k","type":"hold","end":296},
    {"time":296,"key":"f","type":"hold","end":298},
    {"time":296,"key":"d","type":"hold","end":298},
    {"time":299,"key":"j","type":"hold","end":300},
    {"time":299,"key":"f","type":"hold","end":300},
    {"time":299,"key":"d","type":"hold","end":300},
    {"time":299,"key":"k","type":"hold","end":300},
    {"time":301,"key":"j","type":"tap"},
    {"time":301,"key":"k","type":"tap"},
    {"time":302,"key":"f","type":"tap"},
    {"time":302,"key":"d","type":"tap"},
    {"time":303,"key":"j","type":"tap"},
    {"time":303,"key":"k","type":"tap"},
    {"time":304,"key":"f","type":"tap"},
    {"time":304,"key":"d","type":"tap"},
    {"time":305,"key":"j","type":"tap"},
    {"time":305,"key":"k","type":"tap"},
    {"time":306,"key":"d","type":"tap"},
    {"time":306,"key":"f","type":"tap"},
    {"time":307,"key":"j","type":"hold","end":308},
    {"time":307,"key":"k","type":"hold","end":308},
    {"time":308,"key":"d","type":"flick"},
    {"time":308,"key":"f","type":"flick"},
    {"time":309,"key":"j","type":"tap"},
    {"time":309,"key":"k","type":"tap"},
    {"time":310,"key":"d","type":"tap"},
    {"time":310,"key":"f","type":"tap"},
    {"time":311,"key":"j","type":"tap"},
    {"time":311,"key":"k","type":"tap"},
    {"time":312,"key":"d","type":"tap"},
    {"time":312,"key":"f","type":"tap"},
    {"time":313,"key":"j","type":"hold","end":315},
    {"time":313,"key":"k","type":"hold","end":315},
    {"time":315,"key":"d","type":"hold","end":316.5},
    {"time":315,"key":"f","type":"hold","end":316.5},
    {"time":316.5,"key":"j","type":"flick"},
    {"time":316.5,"key":"k","type":"flick"},
    {"time":317.5,"key":"d","type":"tap"},
    {"time":317.5,"key":"f","type":"tap"},
    {"time":318.5,"key":"j","type":"tap"},
    {"time":318.5,"key":"k","type":"tap"},
    {"time":319.5,"key":"d","type":"tap"},
    {"time":319.5,"key":"f","type":"tap"},
    {"time":320.5,"key":"j","type":"tap"},
    {"time":320.5,"key":"k","type":"tap"},
    {"time":321.5,"key":"d","type":"tap"},
    {"time":321.5,"key":"f","type":"tap"},
    {"time":322.5,"key":"j","type":"tap"},
    {"time":322.5,"key":"k","type":"tap"},
    {"time":323.5,"key":"d","type":"tap"},
    {"time":323.5,"key":"f","type":"tap"},
    {"time":324.5,"key":"j","type":"hold","end":325.5},
    {"time":324.5,"key":"k","type":"hold","end":325.5},
    {"time":324.5,"key":"f","type":"hold","end":325.5},
    {"time":324.5,"key":"d","type":"hold","end":325.5},
    {"time":326.5,"key":"d","type":"flick"},
    {"time":326.5,"key":"j","type":"flick"},
    {"time":326.5,"key":"f","type":"flick"},
    {"time":326.5,"key":"k","type":"flick"},
    {"time":327.5,"key":"d","type":"flick"},
    {"time":327.5,"key":"f","type":"flick"},
    {"time":327.5,"key":"j","type":"flick"},
    {"time":327.5,"key":"k","type":"flick"},
    {"time":328.5,"key":"d","type":"flick"},
    {"time":328.5,"key":"f","type":"flick"},
    {"time":328.5,"key":"j","type":"flick"},
    {"time":328.5,"key":"k","type":"flick"},
    {"time":329.5,"key":"k","type":"hold","end":330.5},
    {"time":329.5,"key":"j","type":"hold","end":330.5},
    {"time":330.5,"key":"f","type":"hold","end":331.5},
    {"time":330.5,"key":"d","type":"hold","end":331.5},
    {"time":332.5,"key":"j","type":"tap"},
    {"time":332.5,"key":"k","type":"tap"},
    {"time":333.5,"key":"d","type":"tap"},
    {"time":333.5,"key":"f","type":"tap"},
    {"time":334.5,"key":"j","type":"tap"},
    {"time":334.5,"key":"k","type":"tap"},
    {"time":335.5,"key":"d","type":"tap"},
    {"time":335.5,"key":"f","type":"tap"},
    {"time":336.5,"key":"j","type":"tap"},
    {"time":336.5,"key":"k","type":"tap"},
    {"time":337.5,"key":"d","type":"tap"},
    {"time":337.5,"key":"f","type":"tap"},
    {"time":338.5,"key":"j","type":"tap"},
    {"time":338.5,"key":"k","type":"tap"},
    {"time":339.5,"key":"d","type":"tap"},
    {"time":339.5,"key":"f","type":"tap"},
    {"time":340.5,"key":"k","type":"tap"},
    {"time":341.5,"key":"j","type":"tap"},
    {"time":342.5,"key":"f","type":"tap"},
    {"time":343.5,"key":"d","type":"tap"},
    {"time":344.5,"key":"f","type":"tap"},
    {"time":345.5,"key":"j","type":"tap"},
    {"time":346.5,"key":"k","type":"tap"},
    {"time":347.5,"key":"d","type":"flick"},
    {"time":347.5,"key":"f","type":"flick"},
    {"time":347.5,"key":"j","type":"flick"},
    {"time":347.5,"key":"k","type":"flick"},
    {"time":349,"key":"d","type":"hold","end":363.5},
    {"time":349,"key":"k","type":"hold","end":363.5},
    {"time":349,"key":"f","type":"tap"},
    {"time":350,"key":"f","type":"tap"},
    {"time":351,"key":"j","type":"tap"},
    {"time":351.5,"key":"f","type":"tap"},
    {"time":352.5,"key":"j","type":"tap"},
    {"time":353.5,"key":"f","type":"tap"},
    {"time":354.5,"key":"j","type":"tap"},
    {"time":355,"key":"f","type":"tap"},
    {"time":356,"key":"f","type":"hold","end":371.5},
    {"time":356,"key":"j","type":"hold","end":371.5},
    {"time":364.5,"key":"k","type":"tap"},
    {"time":365.5,"key":"d","type":"tap"},
    {"time":366.5,"key":"k","type":"tap"},
    {"time":367,"key":"d","type":"tap"},
    {"time":368,"key":"k","type":"tap"},
    {"time":369,"key":"d","type":"tap"},
    {"time":370,"key":"k","type":"tap"},
    {"time":370.5,"key":"d","type":"tap"},
    {"time":371.5,"key":"k","type":"tap"},
    {"time":372.5,"key":"k","type":"tap"},
    {"time":374.5,"key":"j","type":"tap"},
    {"time":376.5,"key":"f","type":"tap"},
    {"time":378.5,"key":"d","type":"tap"},
    {"time":380.5,"key":"j","type":"tap"},
    {"time":380.5,"key":"k","type":"tap"},
    {"time":381.5,"key":"d","type":"tap"},
    {"time":381.5,"key":"f","type":"tap"},
    {"time":382.5,"key":"j","type":"tap"},
    {"time":382.5,"key":"k","type":"tap"},
    {"time":383,"key":"f","type":"tap"},
    {"time":383,"key":"d","type":"tap"},
    {"time":384,"key":"j","type":"tap"},
    {"time":384,"key":"k","type":"tap"},
    {"time":385,"key":"f","type":"tap"},
    {"time":385,"key":"d","type":"tap"},
    {"time":386,"key":"j","type":"tap"},
    {"time":386,"key":"k","type":"tap"},
    {"time":386.5,"key":"d","type":"tap"},
    {"time":386.5,"key":"f","type":"tap"},
    {"time":387.5,"key":"d","type":"hold","end":388.5},
    {"time":387.5,"key":"f","type":"hold","end":388.5},
    {"time":387.5,"key":"j","type":"hold","end":388.5},
    {"time":387.5,"key":"k","type":"hold","end":388.5},
    {"time":389.5,"key":"d","type":"tap"},
    {"time":389.5,"key":"f","type":"tap"},
    {"time":390.5,"key":"j","type":"tap"},
    {"time":390.5,"key":"k","type":"tap"},
    {"time":391,"key":"d","type":"tap"},
    {"time":391,"key":"f","type":"tap"},
    {"time":392,"key":"j","type":"tap"},
    {"time":392,"key":"k","type":"tap"},
    {"time":393,"key":"d","type":"tap"},
    {"time":393,"key":"f","type":"tap"},
    {"time":393.5,"key":"j","type":"tap"},
    {"time":393.5,"key":"k","type":"tap"},
    {"time":394.5,"key":"d","type":"tap"},
    {"time":394.5,"key":"f","type":"tap"},
    {"time":395.5,"key":"j","type":"tap"},
    {"time":395.5,"key":"k","type":"tap"},
    {"time":396.5,"key":"d","type":"hold","end":403.5},
    {"time":396.5,"key":"f","type":"hold","end":403.5},
    {"time":397.5,"key":"k","type":"tap"},
    {"time":398.5,"key":"j","type":"tap"},
    {"time":399,"key":"k","type":"tap"},
    {"time":400,"key":"j","type":"tap"},
    {"time":401,"key":"k","type":"tap"},
    {"time":401.5,"key":"j","type":"tap"},
    {"time":402.5,"key":"k","type":"tap"},
    {"time":403.5,"key":"j","type":"tap"},
    {"time":404.5,"key":"f","type":"tap"},
    {"time":404.5,"key":"k","type":"hold","end":411.5},
    {"time":404.5,"key":"j","type":"hold","end":411.5},
    {"time":405.5,"key":"d","type":"tap"},
    {"time":406.5,"key":"f","type":"tap"},
    {"time":407,"key":"d","type":"tap"},
    {"time":408,"key":"f","type":"tap"},
    {"time":409,"key":"d","type":"tap"},
    {"time":410,"key":"f","type":"tap"},
    {"time":410.5,"key":"d","type":"tap"},
    {"time":411.5,"key":"f","type":"tap"},
    {"time":412.5,"key":"d","type":"hold","end":426.5},
    {"time":412.5,"key":"f","type":"hold","end":426.5},
    {"time":412.5,"key":"j","type":"flick"},
    {"time":412.5,"key":"k","type":"flick"},
    {"time":413.5,"key":"k","type":"tap"},
    {"time":414.5,"key":"j","type":"tap"},
    {"time":415,"key":"k","type":"tap"},
    {"time":416,"key":"j","type":"tap"},
    {"time":417,"key":"k","type":"tap"},
    {"time":418,"key":"j","type":"tap"},
    {"time":418.5,"key":"k","type":"tap"},
    {"time":419.5,"key":"j","type":"tap"},
    {"time":420.5,"key":"j","type":"hold","end":421.5},
    {"time":421.5,"key":"k","type":"hold","end":423.5},
    {"time":423.5,"key":"j","type":"tap"},
    {"time":424.5,"key":"k","type":"hold","end":425.5},
    {"time":426.5,"key":"j","type":"tap"},
    {"time":428.5,"key":"k","type":"hold","end":442.5},
    {"time":428.5,"key":"j","type":"hold","end":442.5},
    {"time":428.5,"key":"f","type":"tap"},
    {"time":429.5,"key":"d","type":"tap"},
    {"time":430.5,"key":"f","type":"tap"},
    {"time":431,"key":"d","type":"tap"},
    {"time":432,"key":"f","type":"tap"},
    {"time":433,"key":"d","type":"tap"},
    {"time":434,"key":"f","type":"tap"},
    {"time":434.5,"key":"d","type":"tap"},
    {"time":435.5,"key":"f","type":"tap"},
    {"time":436.5,"key":"d","type":"hold","end":437.5},
    {"time":437.5,"key":"f","type":"hold","end":439.5},
    {"time":439.5,"key":"d","type":"tap"},
    {"time":440.5,"key":"f","type":"hold","end":441.5},
    {"time":442.5,"key":"d","type":"tap"},
    {"time":443.5,"key":"f","type":"tap"},
    {"time":444.5,"key":"d","type":"hold","end":450.5},
    {"time":444.5,"key":"k","type":"hold","end":450.5},
    {"time":444.5,"key":"j","type":"tap"},
    {"time":445.5,"key":"f","type":"tap"},
    {"time":446.5,"key":"j","type":"tap"},
    {"time":447,"key":"f","type":"tap"},
    {"time":448,"key":"j","type":"tap"},
    {"time":449,"key":"f","type":"tap"},
    {"time":449.5,"key":"j","type":"tap"},
    {"time":450.5,"key":"f","type":"hold","end":460.5},
    {"time":450.5,"key":"j","type":"hold","end":460.5},
    {"time":452.5,"key":"k","type":"tap"},
    {"time":453.5,"key":"d","type":"tap"},
    {"time":454.5,"key":"k","type":"tap"},
    {"time":455,"key":"d","type":"tap"},
    {"time":456,"key":"k","type":"tap"},
    {"time":457,"key":"d","type":"tap"},
    {"time":458,"key":"k","type":"tap"},
    {"time":458.5,"key":"d","type":"tap"},
    {"time":459.5,"key":"k","type":"tap"},
    {"time":460.5,"key":"d","type":"tap"},
    {"time":461.5,"key":"k","type":"tap"},
    {"time":461.5,"key":"j","type":"tap"},
    {"time":462.5,"key":"d","type":"tap"},
    {"time":462.5,"key":"f","type":"tap"},
    {"time":463,"key":"j","type":"tap"},
    {"time":463,"key":"k","type":"tap"},
    {"time":464,"key":"d","type":"tap"},
    {"time":464,"key":"f","type":"tap"},
    {"time":465,"key":"k","type":"tap"},
    {"time":465,"key":"j","type":"tap"},
    {"time":466,"key":"d","type":"tap"},
    {"time":466,"key":"f","type":"tap"},
    {"time":466.5,"key":"j","type":"tap"},
    {"time":466.5,"key":"k","type":"tap"},
    {"time":467.5,"key":"d","type":"tap"},
    {"time":467.5,"key":"f","type":"tap"},
    {"time":468.5,"key":"j","type":"tap"},
    {"time":468.5,"key":"k","type":"tap"},
    {"time":469.5,"key":"d","type":"tap"},
    {"time":469.5,"key":"f","type":"tap"},
    {"time":470.5,"key":"j","type":"tap"},
    {"time":470.5,"key":"k","type":"tap"},
    {"time":471,"key":"d","type":"tap"},
    {"time":471,"key":"f","type":"tap"},
    {"time":472,"key":"j","type":"tap"},
    {"time":472,"key":"k","type":"tap"},
    {"time":473,"key":"d","type":"tap"},
    {"time":473,"key":"f","type":"tap"},
    {"time":473.5,"key":"j","type":"tap"},
    {"time":473.5,"key":"k","type":"tap"},
    {"time":474.5,"key":"d","type":"tap"},
    {"time":474.5,"key":"f","type":"tap"},
    {"time":475.5,"key":"j","type":"tap"},
    {"time":475.5,"key":"k","type":"tap"},
    {"time":476.5,"key":"d","type":"hold","end":505.5},
    {"time":476.5,"key":"k","type":"hold","end":505.5},
    {"time":476.5,"key":"j","type":"tap"},
    {"time":477.5,"key":"f","type":"tap"},
    {"time":478.5,"key":"j","type":"tap"},
    {"time":479.5,"key":"f","type":"tap"},
    {"time":480.5,"key":"j","type":"tap"},
    {"time":481.5,"key":"f","type":"tap"},
    {"time":482.5,"key":"j","type":"tap"},
    {"time":483.5,"key":"f","type":"tap"},
    {"time":484.5,"key":"j","type":"flick"},
    {"time":485.5,"key":"f","type":"tap"},
    {"time":486.5,"key":"j","type":"tap"},
    {"time":487.5,"key":"f","type":"tap"},
    {"time":488.5,"key":"j","type":"tap"},
    {"time":489.5,"key":"f","type":"tap"},
    {"time":490.5,"key":"j","type":"tap"},
    {"time":491.5,"key":"f","type":"tap"},
    {"time":492.5,"key":"j","type":"flick"},
    {"time":493.5,"key":"f","type":"flick"},
    {"time":494.5,"key":"j","type":"flick"},
    {"time":495.5,"key":"f","type":"flick"},
    {"time":496.5,"key":"j","type":"flick"},
    {"time":497.5,"key":"f","type":"flick"},
    {"time":498.5,"key":"j","type":"flick"},
    {"time":499.5,"key":"f","type":"flick"},
    {"time":500.5,"key":"j","type":"flick"},
    {"time":501.5,"key":"f","type":"flick"},
    {"time":502.5,"key":"j","type":"flick"},
    {"time":503.5,"key":"f","type":"flick"},
    {"time":504.5,"key":"j","type":"flick"},
    {"time":504.5,"key":"f","type":"flick"},
    {"time":505.5,"key":"f","type":"flick"},
    {"time":505.5,"key":"j","type":"flick"},
    {"time":507,"key":"d","type":"hold","end":508},
    {"time":507,"key":"f","type":"hold","end":508},
    {"time":507,"key":"j","type":"hold","end":508},
    {"time":507,"key":"k","type":"hold","end":508},
    {"time":509,"key":"j","type":"tap"},
    {"time":509,"key":"k","type":"tap"},
    {"time":510,"key":"d","type":"tap"},
    {"time":510,"key":"f","type":"tap"},
    {"time":511,"key":"j","type":"tap"},
    {"time":511,"key":"k","type":"tap"},
    {"time":512,"key":"d","type":"tap"},
    {"time":512,"key":"f","type":"tap"},
    {"time":513,"key":"j","type":"tap"},
    {"time":513,"key":"k","type":"tap"},
    {"time":514,"key":"d","type":"tap"},
    {"time":514,"key":"f","type":"tap"},
    {"time":515,"key":"j","type":"hold","end":516},
    {"time":515,"key":"k","type":"hold","end":516},
    {"time":517,"key":"d","type":"hold","end":518},
    {"time":517,"key":"f","type":"hold","end":518},
    {"time":519,"key":"j","type":"tap"},
    {"time":519,"key":"k","type":"tap"},
    {"time":520,"key":"d","type":"tap"},
    {"time":520,"key":"f","type":"tap"},
    {"time":521,"key":"j","type":"tap"},
    {"time":521,"key":"k","type":"tap"},
    {"time":522,"key":"d","type":"hold","end":524},
    {"time":522,"key":"f","type":"hold","end":524},
    {"time":522,"key":"j","type":"hold","end":524},
    {"time":522,"key":"k","type":"hold","end":524},
    {"time":525,"key":"j","type":"tap"},
    {"time":525,"key":"k","type":"tap"},
    {"time":526,"key":"d","type":"tap"},
    {"time":526,"key":"f","type":"tap"},
    {"time":527,"key":"j","type":"tap"},
    {"time":527,"key":"k","type":"tap"},
    {"time":528,"key":"d","type":"tap"},
    {"time":528,"key":"f","type":"tap"},
    {"time":529,"key":"j","type":"tap"},
    {"time":529,"key":"k","type":"tap"},
    {"time":530,"key":"d","type":"tap"},
    {"time":530,"key":"f","type":"tap"},
    {"time":531,"key":"j","type":"tap"},
    {"time":531,"key":"k","type":"tap"},
    {"time":532,"key":"d","type":"tap"},
    {"time":532,"key":"f","type":"tap"},
    {"time":533,"key":"j","type":"hold","end":534},
    {"time":533,"key":"k","type":"hold","end":534},
    {"time":535,"key":"d","type":"hold","end":536},
    {"time":535,"key":"f","type":"hold","end":536},
    {"time":537,"key":"j","type":"hold","end":538},
    {"time":537,"key":"k","type":"hold","end":538},
    {"time":538,"key":"d","type":"hold","end":540},
    {"time":538,"key":"f","type":"hold","end":540},
    {"time":541,"key":"j","type":"tap"},
    {"time":541,"key":"k","type":"tap"},
    {"time":542,"key":"d","type":"tap"},
    {"time":542,"key":"f","type":"tap"},
    {"time":543,"key":"j","type":"tap"},
    {"time":543,"key":"k","type":"tap"},
    {"time":544,"key":"d","type":"tap"},
    {"time":544,"key":"f","type":"tap"},
    {"time":545,"key":"j","type":"flick"},
    {"time":545,"key":"k","type":"flick"},
    {"time":546,"key":"d","type":"flick"},
    {"time":546,"key":"f","type":"flick"},
    {"time":547,"key":"j","type":"hold","end":548},
    {"time":547,"key":"k","type":"hold","end":548},
    {"time":548,"key":"f","type":"hold","end":552},
    {"time":548,"key":"d","type":"hold","end":552},
    {"time":553,"key":"j","type":"flick"},
    {"time":553,"key":"k","type":"flick"},
    {"time":554,"key":"d","type":"flick"},
    {"time":554,"key":"f","type":"flick"},
    {"time":555,"key":"k","type":"tap"},
    {"time":555,"key":"j","type":"tap"},
    {"time":556,"key":"f","type":"hold","end":557},
    {"time":556,"key":"d","type":"hold","end":557},
    {"time":557,"key":"j","type":"hold","end":558},
    {"time":557,"key":"k","type":"hold","end":558},
    {"time":558,"key":"f","type":"hold","end":559},
    {"time":558,"key":"d","type":"hold","end":559},
    {"time":559,"key":"j","type":"hold","end":560},
    {"time":559,"key":"k","type":"hold","end":560},
    {"time":561,"key":"d","type":"flick"},
    {"time":561,"key":"f","type":"flick"},
    {"time":562,"key":"j","type":"flick"},
    {"time":562,"key":"k","type":"flick"},
    {"time":563,"key":"d","type":"flick"},
    {"time":563,"key":"f","type":"flick"},
    {"time":564,"key":"j","type":"flick"},
    {"time":564,"key":"k","type":"flick"},
    {"time":564,"key":"d","type":"flick"},
    {"time":564,"key":"f","type":"flick"},
    {"time":566,"key":"d","type":"flick"},
    {"time":566,"key":"f","type":"flick"},
    {"time":566,"key":"j","type":"flick"},
    {"time":566,"key":"k","type":"flick"},
    {"time":567,"key":"d","type":"flick"},
    {"time":567,"key":"f","type":"flick"},
    {"time":567,"key":"j","type":"flick"},
    {"time":567,"key":"k","type":"flick"},
    {"time":569,"key":"d","type":"flick"},
    {"time":569,"key":"f","type":"flick"},
    {"time":569,"key":"k","type":"flick"},
    {"time":569,"key":"j","type":"flick"},
    {"time":570.5,"key":"d","type":"hold","end":571.5},
    {"time":570.5,"key":"f","type":"hold","end":571.5},
    {"time":570.5,"key":"k","type":"hold","end":571.5},
    {"time":570.5,"key":"j","type":"hold","end":571.5},
    {"time":572.5,"key":"d","type":"flick"},
    {"time":572.5,"key":"f","type":"flick"},
    {"time":572.5,"key":"j","type":"flick"},
    {"time":572.5,"key":"k","type":"flick"},
    {"time":574,"key":"d","type":"flick"},
    {"time":574,"key":"f","type":"flick"},
    {"time":574,"key":"k","type":"flick"},
    {"time":574,"key":"j","type":"flick"},
    {"time":575,"key":"d","type":"flick"},
    {"time":575,"key":"j","type":"flick"},
    {"time":575,"key":"f","type":"flick"},
    {"time":575,"key":"k","type":"flick"},
    {"time":576.5,"key":"d","type":"flick"},
    {"time":576.5,"key":"f","type":"flick"},
    {"time":576.5,"key":"k","type":"flick"},
    {"time":576.5,"key":"j","type":"flick"},
    {"time":580.5,"key":"f","type":"hold","end":581.5},
    {"time":580.5,"key":"j","type":"hold","end":581.5},
    {"time":581.5,"key":"d","type":"hold","end":582.5},
    {"time":581.5,"key":"k","type":"hold","end":582.5},
    {"time":582.5,"key":"f","type":"hold","end":583.5},
    {"time":582.5,"key":"j","type":"hold","end":583.5},
    {"time":583.5,"key":"d","type":"hold","end":584.5},
    {"time":583.5,"key":"k","type":"hold","end":584.5},
    {"time":584.5,"key":"f","type":"hold","end":585.5},
    {"time":584.5,"key":"j","type":"hold","end":585.5},
    {"time":585.5,"key":"d","type":"hold","end":586.5},
    {"time":585.5,"key":"k","type":"hold","end":586.5},
    {"time":586.5,"key":"f","type":"hold","end":587.5},
    {"time":586.5,"key":"j","type":"hold","end":587.5},
    {"time":587.5,"key":"d","type":"hold","end":588.5},
    {"time":587.5,"key":"k","type":"hold","end":588.5},
    {"time":588.5,"key":"f","type":"hold","end":589.5},
    {"time":588.5,"key":"j","type":"hold","end":589.5},
    {"time":589.5,"key":"d","type":"hold","end":590.5},
    {"time":589.5,"key":"k","type":"hold","end":590.5},
    {"time":590.5,"key":"f","type":"hold","end":591.5},
    {"time":590.5,"key":"j","type":"hold","end":591.5},
    {"time":591.5,"key":"d","type":"hold","end":592.5},
    {"time":591.5,"key":"k","type":"hold","end":592.5},
    {"time":592.5,"key":"f","type":"hold","end":593.5},
    {"time":592.5,"key":"j","type":"hold","end":593.5},
    {"time":595,"key":"d","type":"hold","end":596.5},
    {"time":595,"key":"f","type":"hold","end":596.5},
    {"time":595,"key":"j","type":"hold","end":596.5},
    {"time":595,"key":"k","type":"hold","end":596.5},
    {"time":597.5,"key":"d","type":"hold","end":598.5},
    {"time":597.5,"key":"f","type":"hold","end":598.5},
    {"time":598.5,"key":"j","type":"hold","end":599.5},
    {"time":598.5,"key":"k","type":"hold","end":599.5},
    {"time":599.5,"key":"d","type":"hold","end":600.5},
    {"time":599.5,"key":"f","type":"hold","end":600.5},
    {"time":600.5,"key":"j","type":"hold","end":601.5},
    {"time":600.5,"key":"k","type":"hold","end":601.5},
    {"time":602.5,"key":"d","type":"hold","end":604.5},
    {"time":602.5,"key":"f","type":"hold","end":604.5},
    {"time":602.5,"key":"j","type":"hold","end":604.5},
    {"time":602.5,"key":"k","type":"hold","end":604.5},
    {"time":605.5,"key":"d","type":"flick"},
    {"time":605.5,"key":"f","type":"flick"},
    {"time":606.5,"key":"j","type":"flick"},
    {"time":606.5,"key":"k","type":"flick"},
    {"time":607.5,"key":"d","type":"tap"},
    {"time":607.5,"key":"f","type":"tap"},
    {"time":607.5,"key":"j","type":"tap"},
    {"time":607.5,"key":"k","type":"tap"},
    {"time":608.5,"key":"d","type":"hold","end":611.5},
    {"time":608.5,"key":"f","type":"hold","end":611.5},
    {"time":608.5,"key":"j","type":"hold","end":611.5},
    {"time":608.5,"key":"k","type":"hold","end":611.5},
    {"time":612.5,"key":"d","type":"tap"},
    {"time":612.5,"key":"f","type":"tap"},
    {"time":613.5,"key":"j","type":"tap"},
    {"time":613.5,"key":"k","type":"tap"},
    {"time":614.5,"key":"d","type":"tap"},
    {"time":614.5,"key":"f","type":"tap"},
    {"time":615.5,"key":"j","type":"tap"},
    {"time":615.5,"key":"k","type":"tap"},
    {"time":616.5,"key":"d","type":"hold","end":617.5},
    {"time":616.5,"key":"f","type":"hold","end":617.5},
    {"time":617.5,"key":"j","type":"hold","end":618.5},
    {"time":617.5,"key":"k","type":"hold","end":618.5},
    {"time":618.5,"key":"d","type":"hold","end":619.5},
    {"time":618.5,"key":"f","type":"hold","end":619.5},
    {"time":620.5,"key":"d","type":"hold","end":621.5},
    {"time":620.5,"key":"f","type":"hold","end":621.5},
    {"time":620.5,"key":"j","type":"hold","end":621.5},
    {"time":620.5,"key":"k","type":"hold","end":621.5},
    {"time":622.5,"key":"d","type":"flick"},
    {"time":622.5,"key":"f","type":"flick"},
    {"time":622.5,"key":"j","type":"flick"},
    {"time":622.5,"key":"k","type":"flick"},
    {"time":623.5,"key":"d","type":"flick"},
    {"time":623.5,"key":"f","type":"flick"},
    {"time":623.5,"key":"j","type":"flick"},
    {"time":623.5,"key":"k","type":"flick"},
    {"time":624.5,"key":"d","type":"hold","end":628.5},
    {"time":624.5,"key":"f","type":"hold","end":628.5},
    {"time":624.5,"key":"j","type":"hold","end":628.5},
    {"time":624.5,"key":"k","type":"hold","end":628.5},
    {"time":629.5,"key":"j","type":"flick"},
    {"time":629.5,"key":"k","type":"flick"},
    {"time":630.5,"key":"d","type":"flick"},
    {"time":630.5,"key":"f","type":"flick"},
    {"time":631.5,"key":"j","type":"flick"},
    {"time":631.5,"key":"k","type":"flick"},
    {"time":632.5,"key":"d","type":"flick"},
    {"time":632.5,"key":"f","type":"flick"},
    {"time":633.5,"key":"j","type":"flick"},
    {"time":633.5,"key":"k","type":"flick"},
    {"time":634.5,"key":"d","type":"flick"},
    {"time":634.5,"key":"f","type":"flick"},
    {"time":635.5,"key":"j","type":"flick"},
    {"time":635.5,"key":"k","type":"flick"},
    {"time":636.5,"key":"d","type":"hold","end":639.5},
    {"time":636.5,"key":"f","type":"hold","end":639.5},
    {"time":639.5,"key":"j","type":"hold","end":644.5},
    {"time":639.5,"key":"k","type":"hold","end":644.5},
    {"time":641.5,"key":"d","type":"hold","end":644.5},
    {"time":641.5,"key":"f","type":"hold","end":644.5},
    {"time":645.5,"key":"j","type":"tap"},
    {"time":645.5,"key":"k","type":"tap"},
    {"time":646.5,"key":"d","type":"tap"},
    {"time":646.5,"key":"f","type":"tap"},
    {"time":647.5,"key":"j","type":"tap"},
    {"time":647.5,"key":"k","type":"tap"},
    {"time":648.5,"key":"d","type":"tap"},
    {"time":648.5,"key":"f","type":"tap"},
    {"time":649.5,"key":"j","type":"tap"},
    {"time":649.5,"key":"k","type":"tap"},
    {"time":650.5,"key":"d","type":"flick"},
    {"time":650.5,"key":"f","type":"flick"},
    {"time":651.5,"key":"j","type":"flick"},
    {"time":651.5,"key":"k","type":"flick"},
    {"time":652.5,"key":"d","type":"flick"},
    {"time":652.5,"key":"f","type":"flick"},
    {"time":653.5,"key":"j","type":"flick"},
    {"time":653.5,"key":"k","type":"flick"},
    {"time":654.5,"key":"d","type":"flick"},
    {"time":654.5,"key":"f","type":"flick"},
    {"time":655.5,"key":"j","type":"flick"},
    {"time":655.5,"key":"k","type":"flick"},
    {"time":656.5,"key":"d","type":"flick"},
    {"time":656.5,"key":"f","type":"flick"},
    {"time":657.5,"key":"j","type":"flick"},
    {"time":657.5,"key":"k","type":"flick"},
    {"time":658.5,"key":"d","type":"hold","end":660.5},
    {"time":658.5,"key":"f","type":"hold","end":660.5},
    {"time":658.5,"key":"k","type":"hold","end":660.5},
    {"time":658.5,"key":"j","type":"hold","end":660.5},
    {"time":661.5,"key":"d","type":"flick"},
    {"time":661.5,"key":"f","type":"flick"},
    {"time":662.5,"key":"j","type":"flick"},
    {"time":662.5,"key":"k","type":"flick"},
    {"time":663.5,"key":"d","type":"flick"},
    {"time":663.5,"key":"f","type":"flick"},
    {"time":664.5,"key":"j","type":"flick"},
    {"time":664.5,"key":"k","type":"flick"},
    {"time":665.5,"key":"d","type":"flick"},
    {"time":665.5,"key":"f","type":"flick"},
    {"time":666.5,"key":"j","type":"flick"},
    {"time":666.5,"key":"k","type":"flick"},
    {"time":667.5,"key":"d","type":"hold","end":668.5},
    {"time":667.5,"key":"f","type":"hold","end":668.5},
    {"time":667.5,"key":"j","type":"hold","end":668.5},
    {"time":667.5,"key":"k","type":"hold","end":668.5},
    {"time":669.5,"key":"d","type":"hold","end":670.5},
    {"time":669.5,"key":"f","type":"hold","end":670.5},
    {"time":670.5,"key":"j","type":"hold","end":671.5},
    {"time":670.5,"key":"k","type":"hold","end":671.5},
    {"time":672.5,"key":"j","type":"hold","end":676},
    {"time":672.5,"key":"k","type":"hold","end":676},
    {"time":672.5,"key":"f","type":"hold","end":676},
    {"time":672.5,"key":"d","type":"hold","end":676},
    {"time":677,"key":"j","type":"tap"},
    {"time":677,"key":"k","type":"tap"},
    {"time":678,"key":"d","type":"tap"},
    {"time":678,"key":"f","type":"tap"},
    {"time":679,"key":"j","type":"tap"},
    {"time":679,"key":"k","type":"tap"},
    {"time":680,"key":"f","type":"tap"},
    {"time":680,"key":"d","type":"tap"},
    {"time":681,"key":"j","type":"tap"},
    {"time":681,"key":"k","type":"tap"},
    {"time":682,"key":"d","type":"tap"},
    {"time":682,"key":"f","type":"tap"},
    {"time":683,"key":"k","type":"tap"},
    {"time":684,"key":"j","type":"tap"},
    {"time":685,"key":"f","type":"tap"},
    {"time":686,"key":"d","type":"flick"},
    {"time":686,"key":"f","type":"flick"},
    {"time":686,"key":"k","type":"flick"},
    {"time":686,"key":"j","type":"flick"},
    {"time":687,"key":"d","type":"flick"},
    {"time":687,"key":"j","type":"flick"},
    {"time":687,"key":"f","type":"flick"},
    {"time":687,"key":"k","type":"flick"},
    {"time":688,"key":"d","type":"flick"},
    {"time":688,"key":"j","type":"flick"},
    {"time":688,"key":"f","type":"flick"},
    {"time":688,"key":"k","type":"flick"},
    {"time":689,"key":"k","type":"tap"},
    {"time":689.5,"key":"j","type":"tap"},
    {"time":690,"key":"f","type":"tap"},
    {"time":690.5,"key":"d","type":"tap"},
    {"time":691,"key":"f","type":"tap"},
    {"time":691.5,"key":"j","type":"tap"},
    {"time":692,"key":"k","type":"tap"},
    {"time":693,"key":"d","type":"flick"},
    {"time":693,"key":"f","type":"flick"},
    {"time":694,"key":"j","type":"flick"},
    {"time":694,"key":"k","type":"flick"},
    {"time":695,"key":"d","type":"flick"},
    {"time":695,"key":"f","type":"flick"},
    {"time":696,"key":"j","type":"flick"},
    {"time":696,"key":"k","type":"flick"},
    {"time":697,"key":"d","type":"flick"},
    {"time":697,"key":"f","type":"flick"},
    {"time":698,"key":"j","type":"flick"},
    {"time":698,"key":"k","type":"flick"},
    {"time":699,"key":"d","type":"tap"},
    {"time":699.5,"key":"f","type":"tap"},
    {"time":700,"key":"j","type":"tap"},
    {"time":700.5,"key":"k","type":"tap"},
    {"time":701,"key":"j","type":"tap"},
    {"time":701.5,"key":"f","type":"tap"},
    {"time":702,"key":"d","type":"tap"},
    {"time":702.5,"key":"f","type":"flick"},
    {"time":703,"key":"j","type":"flick"},
    {"time":703.5,"key":"k","type":"flick"},
    {"time":704,"key":"j","type":"flick"},
    {"time":704.5,"key":"f","type":"flick"},
    {"time":705,"key":"d","type":"flick"},
    {"time":705.5,"key":"f","type":"flick"},
    {"time":706,"key":"j","type":"flick"},
    {"time":706.5,"key":"k","type":"flick"},
    {"time":707,"key":"j","type":"flick"},
    {"time":707.5,"key":"f","type":"flick"},
    {"time":708,"key":"d","type":"flick"},
    {"time":709,"key":"j","type":"tap"},
    {"time":709,"key":"k","type":"tap"},
    {"time":710,"key":"d","type":"tap"},
    {"time":710,"key":"f","type":"tap"},
    {"time":711,"key":"j","type":"tap"},
    {"time":711,"key":"k","type":"tap"},
    {"time":712,"key":"d","type":"tap"},
    {"time":712,"key":"f","type":"tap"},
    {"time":713,"key":"j","type":"tap"},
    {"time":713,"key":"k","type":"tap"},
    {"time":714,"key":"f","type":"tap"},
    {"time":714,"key":"d","type":"tap"},
    {"time":715,"key":"j","type":"tap"},
    {"time":715,"key":"k","type":"tap"},
    {"time":716,"key":"d","type":"tap"},
    {"time":716,"key":"f","type":"tap"},
    {"time":717,"key":"j","type":"tap"},
    {"time":717,"key":"k","type":"tap"},
    {"time":718,"key":"d","type":"tap"},
    {"time":718,"key":"f","type":"tap"},
    {"time":719,"key":"j","type":"tap"},
    {"time":719,"key":"k","type":"tap"},
    {"time":720,"key":"d","type":"tap"},
    {"time":720,"key":"f","type":"tap"},
    {"time":721,"key":"j","type":"tap"},
    {"time":721,"key":"k","type":"tap"},
    {"time":722,"key":"f","type":"tap"},
    {"time":722,"key":"d","type":"tap"},
    {"time":723,"key":"k","type":"tap"},
    {"time":723,"key":"j","type":"tap"},
    {"time":724,"key":"d","type":"hold","end":725},
    {"time":724,"key":"f","type":"hold","end":725},
    {"time":726,"key":"j","type":"tap"},
    {"time":726,"key":"k","type":"tap"},
    {"time":727,"key":"d","type":"tap"},
    {"time":727,"key":"f","type":"tap"},
    {"time":728,"key":"j","type":"tap"},
    {"time":728,"key":"k","type":"tap"},
    {"time":729,"key":"d","type":"tap"},
    {"time":729,"key":"f","type":"tap"},
    {"time":730,"key":"k","type":"tap"},
    {"time":730.5,"key":"j","type":"tap"},
    {"time":731,"key":"f","type":"tap"},
    {"time":731.5,"key":"d","type":"tap"},
    {"time":732,"key":"f","type":"tap"},
    {"time":732.5,"key":"j","type":"tap"},
    {"time":733,"key":"k","type":"tap"},
    {"time":733.5,"key":"j","type":"tap"},
    {"time":734,"key":"f","type":"tap"},
    {"time":734.5,"key":"d","type":"tap"},
    {"time":735.5,"key":"j","type":"tap"},
    {"time":735.5,"key":"k","type":"tap"},
    {"time":736.5,"key":"d","type":"tap"},
    {"time":736.5,"key":"f","type":"tap"},
    {"time":737.5,"key":"j","type":"tap"},
    {"time":737.5,"key":"k","type":"tap"},
    {"time":738.5,"key":"d","type":"tap"},
    {"time":738.5,"key":"f","type":"tap"},
    {"time":739.5,"key":"j","type":"tap"},
    {"time":739.5,"key":"k","type":"tap"},
    {"time":740.5,"key":"d","type":"tap"},
    {"time":740.5,"key":"f","type":"tap"},
    {"time":741.5,"key":"j","type":"tap"},
    {"time":741.5,"key":"k","type":"tap"},
    {"time":743.5,"key":"d","type":"tap"},
    {"time":743.5,"key":"f","type":"tap"},
    {"time":746,"key":"j","type":"tap"},
    {"time":746,"key":"k","type":"tap"},
    {"time":748,"key":"d","type":"tap"},
    {"time":748,"key":"f","type":"tap"},
    {"time":750,"key":"j","type":"tap"},
    {"time":750,"key":"k","type":"tap"},
    {"time":752,"key":"d","type":"tap"},
    {"time":752,"key":"f","type":"tap"},
    {"time":754,"key":"j","type":"tap"},
    {"time":754,"key":"k","type":"tap"},
    {"time":756.5,"key":"d","type":"tap"},
    {"time":756.5,"key":"f","type":"tap"},
    {"time":758,"key":"j","type":"tap"},
    {"time":758,"key":"k","type":"tap"},
    {"time":760,"key":"d","type":"tap"},
    {"time":760,"key":"f","type":"tap"},
    {"time":762.5,"key":"j","type":"tap"},
    {"time":762.5,"key":"k","type":"tap"},
    {"time":764.5,"key":"d","type":"tap"},
    {"time":764.5,"key":"f","type":"tap"},
    {"time":766,"key":"j","type":"tap"},
    {"time":766,"key":"k","type":"tap"},
    {"time":768,"key":"d","type":"flick"},
    {"time":768,"key":"f","type":"flick"},
    {"time":768,"key":"j","type":"flick"},
    {"time":768,"key":"k","type":"flick"}
  ]
}